package_name/__init__.py
package_name/module1_name/__init__.py
package_name/module1_name/file1_name.py
package_name/module1_name/file2_name.py
package_name/module2_name/__init__.py
package_name/module2_name/file1_name.py
package_name/module2_name/file2_name.py
package_template_master-0.0.2.dist-info/METADATA
package_template_master-0.0.2.dist-info/WHEEL
package_template_master-0.0.2.dist-info/top_level.txt
package_template_master-0.0.2.dist-info/RECORD
