Metadata-Version: 2.1
Name: package-template-master
Version: 0.0.2
Summary: My short description, because is an example of DIO
Home-page: 
Author: Gracielle
Author-email: 
Requires-Python: >=3.8
